cn_bing_translator/__init__.py
cn_bing_translator/exceptions.py
cn_bing_translator/requesttype.py
cn_bing_translator/translator.py
cn_bing_translator-0.0.3.dist-info/LICENSE
cn_bing_translator-0.0.3.dist-info/METADATA
cn_bing_translator-0.0.3.dist-info/WHEEL
cn_bing_translator-0.0.3.dist-info/top_level.txt
cn_bing_translator-0.0.3.dist-info/RECORD
