Metadata-Version: 2.1
Name: cn-bing-translator
Version: 0.0.3
Summary: microsoft cn.bing translator
Home-page: https://github.com/minibear2021/cn_bing_translator
Author: minibear
License: MIT
Keywords: microsoft bing translator
Classifier: License :: OSI Approved :: MIT License
Classifier: Programming Language :: Python :: 3
License-File: LICENSE
Requires-Dist: requests (>=2.21.0)
